pytradegate/__init__.py
pytradegate/api.py
pytradegate-0.11a0.dist-info/LICENSE
pytradegate-0.11a0.dist-info/METADATA
pytradegate-0.11a0.dist-info/WHEEL
pytradegate-0.11a0.dist-info/top_level.txt
pytradegate-0.11a0.dist-info/RECORD
